{
  "TrainingResults": {
    "AreaUnderRocCurve": 0.50464683645954422,
    "Accuracy": 0.50499478277388976,
    "PositivePrecision": 0.5000720727532163,
    "PositiveRecall": 0.4708348662076684,
    "NegativePrecision": 0.50965716712652864,
    "NegativeRecall": 0.538691833046654,
    "F1Score": 0.48445805014354704,
    "AreaUnderPrecisionRecallCurve": 0.50845792777947219
  },
  "StockSymbol": "GOOG",
  "Parameters": null,
  "IsTrained": true,
  "AverageUpperProbability": 0.0,
  "AverageLowerProbability": 0.0,
  "AverageUpperScore": 0.0,
  "AverageLowerScore": 0.0,
  "FeatureEncoding": "BoW-v2-USA",
  "ModelId": "FFModel-v1"
}