{
  "Date": "2012-05-27T00:00:00",
  "Abstract": "The couple are married in South Salem, N.Y.",
  "WebUrl": "https://www.nytimes.com/2012/05/27/fashion/weddings/lloyd-cheu-douglas-mintz-weddings.html",
  "Snippet": "The couple are married in South Salem, N.Y.",
  "LeadParagraph": "Lloyd Winslow Cheu and Dr. Douglas Nelson Mintz were married Saturday at Le Chateau, a restaurant in South Salem, N.Y. The Rev. M. Frances Sink, a Unitarian Universalist minister, officiated. ",
  "PrintSection": "ST",
  "PrintPage": "14",
  "Source": "The New York Times",
  "PubDate": "2012-05-27T04:47:14+0000",
  "DocumentType": "article",
  "NewsDesk": "Society",
  "SectionName": "Fashion & Style",
  "TypeOfMaterial": "News",
  "Uri": "nyt://article/082c01c5-2a87-5cab-b06a-9c594b29d03f",
  "WordCount": 227,
  "Headline": {
    "Main": "Lloyd Cheu, Douglas Mintz",
    "Kicker": null,
    "ContentKicker": null,
    "PrintHeadline": "Lloyd Cheu, Douglas Mintz",
    "Name": null,
    "Seo": null,
    "Sub": null
  },
  "Keywords": [
    {
      "Name": "subject",
      "Value": "Weddings and Engagements",
      "Rank": 1,
      "Major": "N"
    }
  ],
  "Multimedia": [
    {
      "Rank": 0,
      "SubType": "blog480",
      "Caption": null,
      "Credit": null,
      "Type": "image",
      "Url": "images/2012/05/27/fashion/weddings/27CHEUjpg/27CHEUjpg-blog480.jpg",
      "Height": 360,
      "Width": 480,
      "CropName": "blog480"
    },
    {
      "Rank": 0,
      "SubType": "jumbo",
      "Caption": null,
      "Credit": null,
      "Type": "image",
      "Url": "images/2012/05/27/fashion/weddings/27CHEUjpg/27CHEUjpg-jumbo.jpg",
      "Height": 768,
      "Width": 1024,
      "CropName": "jumbo"
    },
    {
      "Rank": 0,
      "SubType": "popup",
      "Caption": null,
      "Credit": null,
      "Type": "image",
      "Url": "images/2012/05/27/fashion/weddings/27CHEUjpg/27CHEUjpg-popup.jpg",
      "Height": 488,
      "Width": 650,
      "CropName": "popup"
    },
    {
      "Rank": 0,
      "SubType": "superJumbo",
      "Caption": null,
      "Credit": null,
      "Type": "image",
      "Url": "images/2012/05/27/fashion/weddings/27CHEUjpg/27CHEUjpg-superJumbo.jpg",
      "Height": 1536,
      "Width": 2048,
      "CropName": "superJumbo"
    },
    {
      "Rank": 0,
      "SubType": "square320",
      "Caption": null,
      "Credit": null,
      "Type": "image",
      "Url": "images/2012/05/27/fashion/weddings/27CHEUjpg/27CHEUjpg-square320.jpg",
      "Height": 320,
      "Width": 320,
      "CropName": "square320"
    },
    {
      "Rank": 0,
      "SubType": "square640",
      "Caption": null,
      "Credit": null,
      "Type": "image",
      "Url": "images/2012/05/27/fashion/weddings/27CHEUjpg/27CHEUjpg-square640.jpg",
      "Height": 640,
      "Width": 640,
      "CropName": "square640"
    },
    {
      "Rank": 0,
      "SubType": "articleInline",
      "Caption": null,
      "Credit": null,
      "Type": "image",
      "Url": "images/2012/05/27/fashion/weddings/27CHEUjpg/27CHEUjpg-articleInline.jpg",
      "Height": 126,
      "Width": 190,
      "CropName": "articleInline"
    },
    {
      "Rank": 0,
      "SubType": "thumbnail",
      "Caption": null,
      "Credit": null,
      "Type": "image",
      "Url": "images/2012/05/27/fashion/weddings/27CHEUjpg/27CHEUjpg-thumbStandard.jpg",
      "Height": 75,
      "Width": 75,
      "CropName": "thumbStandard"
    },
    {
      "Rank": 0,
      "SubType": "thumbLarge",
      "Caption": null,
      "Credit": null,
      "Type": "image",
      "Url": "images/2012/05/27/fashion/weddings/27CHEUjpg/27CHEUjpg-thumbLarge.jpg",
      "Height": 150,
      "Width": 150,
      "CropName": "thumbLarge"
    }
  ],
  "Byline": {
    "Original": null,
    "Organization": null,
    "Person": []
  }
}